rpz_manager.py
rpz_manager-0.2.dist-info/LICENSE
rpz_manager-0.2.dist-info/METADATA
rpz_manager-0.2.dist-info/WHEEL
rpz_manager-0.2.dist-info/entry_points.txt
rpz_manager-0.2.dist-info/top_level.txt
rpz_manager-0.2.dist-info/zip-safe
rpz_manager-0.2.dist-info/RECORD
