Metadata-Version: 2.1
Name: rpz-manager
Version: 0.2
Summary: Block ads and malicious domains with response policy zones
Home-page: https://github.com/stevekroh/rpz-manager
Author: Steven Kroh
Author-email: steve@kroh.xyz
License: GPLv3
Project-URL: Changelog, https://github.com/stevekroh/rpz-manager/blob/master/CHANGELOG.md
Keywords: dns,rpz,rpz-feed,pihole
Platform: UNKNOWN
Classifier: Development Status :: 1 - Planning
Classifier: Environment :: Console
Classifier: Intended Audience :: System Administrators
Classifier: License :: OSI Approved :: GNU General Public License v3 or later (GPLv3+)
Classifier: Operating System :: POSIX
Classifier: Programming Language :: Python :: 3 :: Only
Classifier: Programming Language :: Python :: 3.6
Classifier: Programming Language :: Python :: 3.7
Classifier: Programming Language :: Python :: 3.8
Classifier: Topic :: Internet :: Name Service (DNS)
Requires-Python: >=3.6
